quicklst/__init__.py
quicklst/distortion_map.npz
quicklst/quicklst.py
quicklst-0.0.3.dist-info/licenses/LICENSE
quicklst-0.0.3.dist-info/METADATA
quicklst-0.0.3.dist-info/WHEEL
quicklst-0.0.3.dist-info/top_level.txt
quicklst-0.0.3.dist-info/RECORD
