Metadata-Version: 2.4
Name: quicklst
Version: 0.0.3
Summary: Read lst files produced by FAST ComTec's mpa system.
Author-email: Joschka Goes <jajo_11@outlook.com>
Project-URL: Homepage, https://github.com/jajo-11/quicklst
Project-URL: Bug Tracker, https://github.com/jajo-11/quicklst/issues
Classifier: Programming Language :: Python :: 3
Classifier: License :: OSI Approved :: MIT License
Classifier: Operating System :: OS Independent
Requires-Python: >=3.7
License-File: LICENSE
Requires-Dist: setuptools
Requires-Dist: numpy
Requires-Dist: numba
Dynamic: license-file
